[
  {
    "CaseTypeID": "CIVIL",
    "ID": "changeOfRepresentation",
    "Label": "change of representation details",
    "FieldType": "ChangeOfRepresentation",
    "SecurityClassification": "Public",
    "Comment": "Field storing noc update details"
  },
  {
    "CaseTypeID": "CIVIL",
    "ID": "casePaymentWaysToPay",
    "Label": "Service Request",
    "FieldType": "WaysToPay",
    "SecurityClassification": "Public"
  },
  {
    "CaseTypeID": "CIVIL",
    "ID": "registrationTypeRespondentOne",
    "Label": "registration information respondent one",
    "FieldType": "Collection",
    "FieldTypeParameter": "RegistrationTypeInformation",
    "SecurityClassification": "Public"
  },
  {
    "CaseTypeID": "CIVIL",
    "ID": "registrationTypeRespondentTwo",
    "Label": "registration information respondent two",
    "FieldType": "Collection",
    "FieldTypeParameter": "RegistrationTypeInformation",
    "SecurityClassification": "Public"
  },
   {
    "CaseTypeID": "CIVIL",
    "ID": "componentLauncher",
    "Label": "Case file view",
    "FieldType": "ComponentLauncher",
    "SecurityClassification": "Public"
  },
  {
    "CaseTypeID": "CIVIL",
    "ID": "trialReadyDocuments",
    "Label": "System generated Case Documents",
    "FieldType": "Collection",
    "FieldTypeParameter": "CaseDocument",
    "SecurityClassification": "Public"
}

]
