[
  {
    "CaseTypeID": "CIVIL",
    "CaseEventID": "CREATE_CASE_FLAGS",
    "AccessControl": [
      {
        "UserRoles": [
          "caseworker-civil-admin",
        ],
        "CRUD": "CRU"
      },
      {
        "UserRoles": [
          "judge-profile",
        ],
        "CRUD": "R"
      }
    ]
  },
  {
    "CaseTypeID": "CIVIL",
    "CaseEventID": "MANAGE_CASE_FLAGS",
    "AccessControl": [
      {
        "UserRoles": [
          "caseworker-civil-admin",
        ],
        "CRUD": "CRU"
      },
      {
        "UserRoles": [
          "judge-profile",
        ],
        "CRUD": "R"
      }
    ]
  }
]
