[
  {
    "RoleName" : "leadership-judge",
    "Authorisation": "",
    "CaseTypeID": "CIVIL",
    "AccessProfiles": "judge-profile,GS_profile,caseflags-viewer",
    "ReadOnly": "N",
    "Disabled": "F",
    "CaseAccessCategories": ""
  },
  {
    "RoleName" : "judge",
    "Authorisation": "",
    "CaseTypeID": "CIVIL",
    "AccessProfiles": "judge-profile,GS_profile,caseflags-viewer",
    "ReadOnly": "N",
    "Disabled": "F",
    "CaseAccessCategories": ""
  },
  {
    "RoleName" : "specific-access-judiciary",
    "Authorisation": "",
    "CaseTypeID": "CIVIL",
    "AccessProfiles": "judge-profile,caseworker-civil,GS_profile,caseflags-viewer",
    "ReadOnly": "Y",
    "Disabled": "F",
    "CaseAccessCategories": ""
  },
  {
    "RoleName" : "challenged-access-judiciary",
    "Authorisation": "",
    "CaseTypeID": "CIVIL",
    "AccessProfiles": "GS_profile,judge-profile,caseworker-civil,caseflags-viewer",
    "ReadOnly": "N",
    "Disabled": "F",
    "CaseAccessCategories": ""
  },
  {
    "RoleName" : "hearing-centre-admin",
    "Authorisation": "",
    "CaseTypeID": "CIVIL",
    "AccessProfiles": "GS_profile,caseworker-civil-admin,hearing-schedule-access,caseflags-admin",
    "ReadOnly": "N",
    "Disabled": "F",
    "CaseAccessCategories": ""
  },
  {
    "RoleName" : "ctsc-team-leader",
    "Authorisation": "",
    "CaseTypeID": "CIVIL",
    "AccessProfiles": "GS_profile,caseworker-civil-admin,caseflags-admin,cui-admin-profile",
    "ReadOnly": "N",
    "Disabled": "F",
    "CaseAccessCategories": ""
  },
  {
    "RoleName" : "ctsc",
    "Authorisation": "",
    "CaseTypeID": "CIVIL",
    "AccessProfiles": "GS_profile,caseworker-civil-admin,caseflags-admin,cui-admin-profile",
    "ReadOnly": "N",
    "Disabled": "F",
    "CaseAccessCategories": ""
  },
  {
    "RoleName" : "nbc-team-leader",
    "Authorisation": "",
    "CaseTypeID": "CIVIL",
    "AccessProfiles": "GS_profile,caseworker-civil-admin,caseflags-admin,cui-nbc-profile",
    "ReadOnly": "N",
    "Disabled": "F",
    "CaseAccessCategories": ""
  },
  {
    "RoleName" : "national-business-centre",
    "Authorisation": "",
    "CaseTypeID": "CIVIL",
    "AccessProfiles": "GS_profile,caseworker-civil-admin,hearing-schedule-access,caseflags-admin,cui-nbc-profile",
    "ReadOnly": "N",
    "Disabled": "F",
    "CaseAccessCategories": ""
  },
  {
    "RoleName" : "hearing-centre-team-leader",
    "Authorisation": "",
    "CaseTypeID": "CIVIL",
    "AccessProfiles": "GS_profile,hearing-schedule-access,caseworker-civil-admin,caseflags-admin",
    "ReadOnly": "N",
    "Disabled": "F",
    "CaseAccessCategories": ""
  },
  {
    "RoleName" : "specific-access-admin",
    "Authorisation": "",
    "CaseTypeID": "CIVIL",
    "AccessProfiles": "GS_profile,legal-adviser,caseworker-civil,caseflags-admin",
    "ReadOnly": "Y",
    "Disabled": "F",
    "CaseAccessCategories": ""
  },
  {
    "RoleName" : "challenged-access-admin",
    "Authorisation": "",
    "CaseTypeID": "CIVIL",
    "AccessProfiles": "GS_profile,legal-adviser,caseworker-civil,caseflags-admin",
    "ReadOnly": "N",
    "Disabled": "F",
    "CaseAccessCategories": ""
  },
  {
    "RoleName" : "task-supervisor",
    "Authorisation": "",
    "CaseTypeID": "CIVIL",
    "AccessProfiles": "GS_profile,cui-admin-profile",
    "ReadOnly": "Y",
    "Disabled": "F",
    "CaseAccessCategories": ""
  },
  {
    "RoleName" : "tribunal-caseworker",
    "Authorisation": "",
    "CaseTypeID": "CIVIL",
    "AccessProfiles": "GS_profile,legal-adviser,caseworker-civil-admin,caseflags-viewer",
    "ReadOnly": "N",
    "Disabled": "F",
    "CaseAccessCategories": ""
  },
  {
    "RoleName" : "senior-tribunal-caseworker",
    "Authorisation": "",
    "CaseTypeID": "CIVIL",
    "AccessProfiles": "GS_profile,legal-adviser,caseworker-civil-admin,caseflags-viewer",
    "ReadOnly": "N",
    "Disabled": "F",
    "CaseAccessCategories": ""
  }
]
