[
  {
    "CaseTypeID": "CIVIL",
    "CaseStateID": "JUDICIAL_REFERRAL",
    "AccessControl": [
      {
        "UserRoles": [
          "judge-profile"
        ],
        "CRUD": "CRU"
      },
      {
        "UserRoles": [
          "caseworker-civil-admin",
          "[APPLICANTSOLICITORONE]",
          "basic-access"
        ],
        "CRUD": "R"
      }
    ]
  },
  {
    "CaseTypeID": "CIVIL",
    "CaseStateID": "JUDICIAL_REFERRAL",
    "AccessControl": [
      {
        "UserRoles": [
          "tribunal-caseworker",
          "hearing-center-admin"
        ],
        "CRUD": "CRU"
      },
      {
        "UserRoles": [
          "caseworker-civil-admin",
          "[APPLICANTSOLICITORONE]"
        ],
        "CRUD": "R"
      }
    ]
  }
]
