[
  {
    "ID": "ExpertLiP",
    "ListElementCode": "caseNeedsAnExpert",
    "ElementLabel": " ",
    "FieldType": "YesOrNo",
    "Searchable": "N",
    "SecurityClassification": "Public"
  },
  {
    "ID": "ExpertLiP",
    "ListElementCode": "expertCanStillExamineDetails",
    "ElementLabel": " ",
    "FieldType": "Text",
    "Searchable": "N",
    "SecurityClassification": "Public"
  },
  {
    "ID": "ExpertLiP",
    "ListElementCode": "expertReportRequired",
    "ElementLabel": " ",
    "FieldType": "YesOrNo",
    "Searchable": "N",
    "SecurityClassification": "Public"
  },
  {
    "ID": "ExpertLiP",
    "ListElementCode": "details",
    "ElementLabel": " ",
    "FieldType": "Collection",
    "FieldTypeParameter": "ExpertReportLiP",
    "Searchable": "N",
    "SecurityClassification": "Public"
  }
]
