[
  {
    "ID": "ReasonUnsuitableSDO",
    "CaseEventID": "Unsuitable_SDO",
    "CaseFieldID": "reasonUnsuitableSDO",
    "ListElementCode": "label",
    "FieldDisplayOrder": 1,
    "DisplayContext": "READONLY"
  },
  {
    "ID": "ReasonUnsuitableSDO",
    "CaseEventID": "Unsuitable_SDO",
    "CaseFieldID": "reasonUnsuitableSDO",
    "ListElementCode": "text",
    "FieldDisplayOrder": 2,
    "DisplayContext": "READONLY"
  },
  {
    "ID": "ReasonUnsuitableSDO",
    "CaseEventID": "Unsuitable_SDO",
    "CaseFieldID": "reasonUnsuitableSDO",
    "ListElementCode": "input",
    "FieldDisplayOrder": 3,
    "DisplayContext": "MANDATORY"
  }
]
