[
  {
    "CaseTypeID": "CIVIL",
    "ListElementCode": "label",
    "ID": "FinalOrderAppeal",
    "ElementLabel": "### The",
    "FieldType": "Label",
    "SecurityClassification": "Public"
  },
  {
    "CaseTypeID": "CIVIL",
    "ListElementCode": "list",
    "ID": "FinalOrderAppeal",
    "ElementLabel": " ",
    "FieldType": "FixedRadioList",
    "FieldTypeParameter": "AppealList",
    "SecurityClassification": "Public"
  },
  {
    "CaseTypeID": "CIVIL",
    "ListElementCode": "otherText",
    "ID": "FinalOrderAppeal",
    "ElementLabel": "Please specify",
    "FieldType": "Text",
    "FieldShowCondition": "list = \"OTHER\"",
    "SecurityClassification": "Public"
  },
  {
    "CaseTypeID": "CIVIL",
    "ListElementCode": "applicationLabel",
    "ID": "FinalOrderAppeal",
    "ElementLabel": "### application for permission to appeal is",
    "FieldType": "Label",
    "SecurityClassification": "Public"
  },
  {
    "CaseTypeID": "CIVIL",
    "ListElementCode": "applicationList",
    "ID": "FinalOrderAppeal",
    "ElementLabel": " ",
    "FieldType": "FixedRadioList",
    "FieldTypeParameter": "ApplicationAppealList",
    "SecurityClassification": "Public"
  },

  {
    "CaseTypeID": "CIVIL",
    "ListElementCode": "appealGrantedRefusedDropdown",
    "ID": "FinalOrderAppeal",
    "ElementLabel": " ",
    "FieldType": "AppealChoiceFirstDropdown",
    "SecurityClassification": "Public",
    "FieldShowCondition": "applicationList = \"GRANTED\" OR applicationList = \"REFUSED\""
  }
]
